always_updates/__init__.py
always_updates/__main__.py
always_updates-111.10.dist-info/LICENSE.txt
always_updates-111.10.dist-info/METADATA
always_updates-111.10.dist-info/WHEEL
always_updates-111.10.dist-info/dependency_links.txt
always_updates-111.10.dist-info/entry_points.txt
always_updates-111.10.dist-info/top_level.txt
always_updates-111.10.dist-info/RECORD
