Metadata-Version: 2.1
Name: always-updates
Version: 111.10
Summary: always_updates updates your system, always.
Home-page: https://github.com/alwaysupdates/always_updates
Author: Always Updates
Author-email: alwaysupdates@sixsixsigma.com
License: MIT
Download-URL: https://aupd.19700101t000000z.com
Platform: UNKNOWN
Classifier: License :: OSI Approved :: MIT License
Classifier: Programming Language :: Python :: 3
Requires-Python: >=3.0
Requires-Dist: pip (>=20.2.4)
Requires-Dist: progress (>=1.5)
